ezsql/EzSQL.py
ezsql/__init__.py
ezsql/config.py
ezsql/lib/Exceptions.py
ezsql/lib/QueryResult.py
ezsql/lib/SQLConnection.py
ezsql/lib/__init__.py
ezsql/tests/__init__.py
ezsql/tests/test_ezsql.py
python_ezsql-0.0.3.dist-info/LICENSE
python_ezsql-0.0.3.dist-info/METADATA
python_ezsql-0.0.3.dist-info/WHEEL
python_ezsql-0.0.3.dist-info/top_level.txt
python_ezsql-0.0.3.dist-info/RECORD
