Metadata-Version: 2.1
Name: python-ezsql
Version: 0.0.3
Summary: This python package is based from python mysql connector
Home-page: https://github.com/Mackhintoshi/EzSQL
Author: Jerick GUtierrez
Classifier: License :: OSI Approved :: MIT License
Classifier: Programming Language :: Python :: 3
License-File: LICENSE
Requires-Dist: mysql-connector-python
